xylo/__init__.py
xylo/core.py
xylo_py-0.1.8.dist-info/licenses/LICENSE
xylo_py-0.1.8.dist-info/METADATA
xylo_py-0.1.8.dist-info/WHEEL
xylo_py-0.1.8.dist-info/top_level.txt
xylo_py-0.1.8.dist-info/RECORD
