Metadata-Version: 2.4
Name: xylo.py
Version: 0.1.8
Summary: A powerful template engine with Python expression evaluation
License-Expression: MIT
Project-URL: Homepage, https://github.com/yourusername/xylo
Project-URL: Repository, https://github.com/yourusername/xylo
Project-URL: Issues, https://github.com/yourusername/xylo/issues
Keywords: template,templating,text processing,markup
Classifier: Development Status :: 4 - Beta
Classifier: Intended Audience :: Developers
Classifier: Operating System :: OS Independent
Classifier: Programming Language :: Python :: 3
Classifier: Programming Language :: Python :: 3.8
Classifier: Programming Language :: Python :: 3.9
Classifier: Programming Language :: Python :: 3.10
Classifier: Programming Language :: Python :: 3.11
Classifier: Programming Language :: Python :: 3.12
Classifier: Programming Language :: Python :: 3.13
Classifier: Topic :: Text Processing :: Markup
Classifier: Topic :: Software Development :: Libraries :: Python Modules
Requires-Python: >=3.8
License-File: LICENSE
Provides-Extra: dev
Requires-Dist: pytest>=7.0; extra == "dev"
Dynamic: license-file
